src/Entropy_LUT_5x5.v
module Entropy_LUT_5x5(
    input [4:0] count,
    output reg [11:0] En5_res
);
    always @(*) begin
        case(count)
            5'd0  : En5_res = 12'd0;
            5'd1  : En5_res = 12'd132;
            5'd2  : En5_res = 12'd207;
            5'd3  : En5_res = 12'd261;
            5'd4  : En5_res = 12'd300;
            5'd5  : En5_res = 12'd330;
            5'd6  : En5_res = 12'd351;
            5'd7  : En5_res = 12'd365;
            5'd8  : En5_res = 12'd373;
            5'd9  : En5_res = 12'd377;
            5'd10 : En5_res = 12'd375;
            5'd11 : En5_res = 12'd370;
            5'd12 : En5_res = 12'd361;
            5'd13 : En5_res = 12'd348;
            5'd14 : En5_res = 12'd333;
            5'd15 : En5_res = 12'd314;
            5'd16 : En5_res = 12'd292;
            5'd17 : En5_res = 12'd269;
            5'd18 : En5_res = 12'd242;
            5'd19 : En5_res = 12'd214;
            5'd20 : En5_res = 12'd183;
            5'd21 : En5_res = 12'd150;
            5'd22 : En5_res = 12'd115;
            5'd23 : En5_res = 12'd79;
            5'd24 : En5_res = 12'd40;
            5'd25 : En5_res = 12'd0;
            
            default: En5_res = 12'd0;
        endcase
    end
endmodule

src/Entropy_LUT_3x3.v
module Entropy_LUT_3x3(
    input wire [3:0] count,
    output reg [8:0] En3_res
);
    always @(*) begin
        case(count)
            4'd0:   En3_res = 9'd0;
            4'd1:   En3_res = 9'd250;
            4'd2:   En3_res = 9'd342;
            4'd3:   En3_res = 9'd375;
            4'd4:   En3_res = 9'd369;
            4'd5:   En3_res = 9'd334;
            4'd6:   En3_res = 9'd277;
            4'd7:   En3_res = 9'd200;
            4'd8:   En3_res = 9'd107;
            4'd9:   En3_res = 9'd0;
            
            default: En3_res = 9'd0;
            endcase 
        end
    endmodule

src/H0.v
module H0( // Tinh Entropy cho phần foreground
    input wire clk,
    input wire rst_n,
    input wire en,

    input wire [4:0] count,
    input wire clear,
    input wire mode, //mode 0 -> 3x3, mode 1 -> 5x5
    output reg [15:0] H0_res
);
    wire [8:0] En3_res;
    wire [11:0] En5_res;

    Entropy_LUT_3x3 inst1(
        .count(count[3:0]),
        .En3_res(En3_res)
    );

    Entropy_LUT_5x5 inst2(
        .count(count),
        .En5_res(En5_res)
    );

    always @(posedge clk or negedge rst_n) begin
        if(~rst_n) begin
            H0_res <= 16'd0;
        end
        else if(clear) begin
            H0_res <= 16'd0;
        end
        else begin
            if(en) begin
                if(count > 0) begin
                    H0_res <= H0_res + ((mode) ? En5_res : En3_res);
                end
            end
        end
    end
endmodule

testbench/tb_H0.v
`timescale 1ns/1ps

module tb_H0;
    reg clk, rst_n, en, clear, mode;
    reg [4:0] count;
    wire [15:0] H0_res;
    reg [15:0] expected;
    integer errors;

    // Instance module H0
    H0 uut (
        .clk(clk), .rst_n(rst_n), .en(en),
        .count(count), .clear(clear), .mode(mode),
        .H0_res(H0_res)
    );

    always #5 clk = ~clk;

    task check_equal;
        input [15:0] got;
        input [15:0] exp;
        input [127:0] msg;
        begin
            if (got !== exp) begin
                errors = errors + 1;
                $display("[FAIL] t=%0t %0s | got=%0d expected=%0d", $time, msg, got, exp);
            end else begin
                $display("[PASS] t=%0t %0s | value=%0d", $time, msg, got);
            end
        end
    endtask

    task apply_and_check;
        input [4:0] i_count;
        input i_mode;
        begin
            mode = i_mode;
            count = i_count;
            clear = 1'b0;

            @(posedge clk);
            #1;

            // H0 chỉ cộng khi count > 0
            if (count > 0) begin
                if (mode == 1'b0)
                    expected = expected + lut3(count[3:0]);
                else
                    expected = expected + lut5(count);
            end

            check_equal(H0_res, expected, "apply_and_check");
        end
    endtask

    function [15:0] lut3;
        input [3:0] c;
        begin
            case (c)
                4'd0: lut3 = 16'd0;
                4'd1: lut3 = 16'd250;
                4'd2: lut3 = 16'd342;
                4'd3: lut3 = 16'd375;
                4'd4: lut3 = 16'd369;
                4'd5: lut3 = 16'd334;
                4'd6: lut3 = 16'd277;
                4'd7: lut3 = 16'd200;
                4'd8: lut3 = 16'd107;
                default: lut3 = 16'd0;
            endcase
        end
    endfunction

    function [15:0] lut5;
        input [4:0] c;
        begin
            case (c)
                5'd0 : lut5 = 16'd0;
                5'd1 : lut5 = 16'd132;
                5'd2 : lut5 = 16'd207;
                5'd3 : lut5 = 16'd261;
                5'd4 : lut5 = 16'd300;
                5'd5 : lut5 = 16'd330;
                5'd6 : lut5 = 16'd351;
                5'd7 : lut5 = 16'd365;
                5'd8 : lut5 = 16'd373;
                5'd9 : lut5 = 16'd377;
                5'd10: lut5 = 16'd375;
                5'd11: lut5 = 16'd370;
                5'd12: lut5 = 16'd361;
                5'd13: lut5 = 16'd348;
                5'd14: lut5 = 16'd333;
                5'd15: lut5 = 16'd314;
                5'd16: lut5 = 16'd292;
                5'd17: lut5 = 16'd269;
                5'd18: lut5 = 16'd242;
                5'd19: lut5 = 16'd214;
                5'd20: lut5 = 16'd183;
                5'd21: lut5 = 16'd150;
                5'd22: lut5 = 16'd115;
                5'd23: lut5 = 16'd79;
                5'd24: lut5 = 16'd40;
                5'd25: lut5 = 16'd0;
                default: lut5 = 16'd0;
            endcase
        end
    endfunction

    initial begin
        $dumpfile("tb_H0.vcd");
        $dumpvars(0, tb_H0);

        clk = 1'b0;
        rst_n = 1'b0;
        en = 1'b0;
        clear = 1'b0;
        mode = 1'b0;
        count = 5'd0;
        expected = 16'd0;
        errors = 0;

        $display("\n==================== TB_H0 START ====================");

        // reset check
        repeat (2) @(posedge clk);
        #1;
        check_equal(H0_res, 16'd0, "after reset low");

        rst_n = 1'b1;
        en = 1'b1;

        // 3x3 mode accumulation
        apply_and_check(5'd4, 1'b0); // +369
        apply_and_check(5'd5, 1'b0); // +334 => 703
        apply_and_check(5'd0, 1'b0); // +0   => 703

        // en gating: hold value when en=0
        en = 1'b0;
        count = 5'd3;
        @(posedge clk);
        #1;
        check_equal(H0_res, expected, "en=0 hold value");

        // clear priority (independent from en)
        clear = 1'b1;
        @(posedge clk);
        #1;
        expected = 16'd0;
        check_equal(H0_res, expected, "clear asserted");
        clear = 1'b0;

        // 5x5 mode accumulation
        en = 1'b1;
        apply_and_check(5'd10, 1'b1); // +375
        apply_and_check(5'd2,  1'b1); // +207 => 582
        apply_and_check(5'd25, 1'b1); // +0   => 582

        if (errors == 0)
            $display("[RESULT] TB_H0 PASSED (no mismatches)");
        else
            $display("[RESULT] TB_H0 FAILED with %0d mismatch(es)", errors);

        $display("===================== TB_H0 END =====================\n");
        #10 $finish;
    end

endmodule

sim/tb_H0.vcd
$date
	Mon Apr  6 13:56:56 2026
$end
$version
	Icarus Verilog
$end
$timescale
	1ps
$end
$scope module tb_H0 $end
$var wire 16 ! H0_res [15:0] $end
$var reg 1 " clear $end
$var reg 1 # clk $end
$var reg 5 $ count [4:0] $end
$var reg 1 % en $end
$var reg 16 & expected [15:0] $end
$var reg 1 ' mode $end
$var reg 1 ( rst_n $end
$var integer 32 ) errors [31:0] $end
$scope function lut3 $end
$var reg 4 * c [3:0] $end
$upscope $end
$scope function lut5 $end
$var reg 5 + c [4:0] $end
$upscope $end
$scope module uut $end
$var wire 1 " clear $end
$var wire 1 # clk $end
$var wire 5 , count [4:0] $end
$var wire 1 % en $end
$var wire 1 ' mode $end
$var wire 1 ( rst_n $end
$var wire 12 - En5_res [11:0] $end
$var wire 9 . En3_res [8:0] $end
$var reg 16 / H0_res [15:0] $end
$scope module inst1 $end
$var wire 4 0 count [3:0] $end
$var reg 9 1 En3_res [8:0] $end
$upscope $end
$scope module inst2 $end
$var wire 5 2 count [4:0] $end
$var reg 12 3 En5_res [11:0] $end
$upscope $end
$upscope $end
$scope task apply_and_check $end
$var reg 5 4 i_count [4:0] $end
$var reg 1 5 i_mode $end
$upscope $end
$scope task check_equal $end
$var reg 16 6 exp [15:0] $end
$var reg 16 7 got [15:0] $end
$var reg 128 8 msg [127:0] $end
$upscope $end
$upscope $end
$enddefinitions $end
$comment Show the parameter values. $end
$dumpall
$end
#0
$dumpvars
bx 8
bx 7
bx 6
x5
bx 4
b0 3
b0 2
b0 1
b0 0
b0 /
b0 .
b0 -
b0 ,
bx +
bx *
b0 )
0(
0'
b0 &
0%
b0 $
0#
0"
b0 !
$end
#5000
1#
#10000
0#
#15000
1#
#16000
b101110001 .
b101110001 1
b100 0
b100101100 -
b100101100 3
b100 $
b100 ,
b100 2
05
b100 4
1%
1(
b11000010110011001110100011001010111001000100000011100100110010101110011011001010111010000100000011011000110111101110111 8
b0 6
b0 7
#20000
0#
#25000
b101110001 !
b101110001 /
1#
#26000
b101001110 .
b101001110 1
b101 0
b101001010 -
b101001010 3
b101 $
b101 ,
b101 2
b101 4
b11000010111000001110000011011000111100101011111011000010110111001100100010111110110001101101000011001010110001101101011 8
b101110001 6
b101110001 7
b101110001 &
b100 *
#30000
0#
#35000
b1010111111 !
b1010111111 /
1#
#36000
b0 .
b0 1
b0 0
b0 -
b0 3
b0 $
b0 ,
b0 2
b0 4
b1010111111 6
b1010111111 7
b1010111111 &
b101 *
#40000
0#
#45000
1#
#46000
b101110111 .
b101110111 1
b11 0
b100000101 -
b100000101 3
b11 $
b11 ,
b11 2
0%
#50000
0#
#55000
1#
#56000
1"
b11001010110111000111101001100000010000001101000011011110110110001100100001000000111011001100001011011000111010101100101 8
#60000
0#
#65000
b0 !
b0 /
1#
#66000
b0 .
b0 1
b1010 0
b101110111 -
b101110111 3
b1010 $
b1010 ,
b1010 2
1'
15
b1010 4
1%
0"
b110001101101100011001010110000101110010001000000110000101110011011100110110010101110010011101000110010101100100 8
b0 6
b0 7
b0 &
#70000
0#
#75000
b101110111 !
b101110111 /
1#
#76000
b101010110 .
b101010110 1
b10 0
b11001111 -
b11001111 3
b10 $
b10 ,
b10 2
b10 4
b11000010111000001110000011011000111100101011111011000010110111001100100010111110110001101101000011001010110001101101011 8
b101110111 6
b101110111 7
b101110111 &
b1010 +
#80000
0#
#85000
b1001000110 !
b1001000110 /
1#
#86000
b0 .
b0 1
b1001 0
b0 -
b0 3
b11001 $
b11001 ,
b11001 2
b11001 4
b1001000110 6
b1001000110 7
b1001000110 &
b10 +
#90000
0#
#95000
1#
#96000
b11001 +
