src/Entropy_LUT_5x5.v
module Entropy_LUT_5x5(
    input [4:0] count,
    output reg [11:0] En5_res
);
    always @(*) begin
        case(count)
            5'd0  : En5_res = 12'd0;
            5'd1  : En5_res = 12'd132;
            5'd2  : En5_res = 12'd207;
            5'd3  : En5_res = 12'd261;
            5'd4  : En5_res = 12'd300;
            5'd5  : En5_res = 12'd330;
            5'd6  : En5_res = 12'd351;
            5'd7  : En5_res = 12'd365;
            5'd8  : En5_res = 12'd373;
            5'd9  : En5_res = 12'd377;
            5'd10 : En5_res = 12'd375;
            5'd11 : En5_res = 12'd370;
            5'd12 : En5_res = 12'd361;
            5'd13 : En5_res = 12'd348;
            5'd14 : En5_res = 12'd333;
            5'd15 : En5_res = 12'd314;
            5'd16 : En5_res = 12'd292;
            5'd17 : En5_res = 12'd269;
            5'd18 : En5_res = 12'd242;
            5'd19 : En5_res = 12'd214;
            5'd20 : En5_res = 12'd183;
            5'd21 : En5_res = 12'd150;
            5'd22 : En5_res = 12'd115;
            5'd23 : En5_res = 12'd79;
            5'd24 : En5_res = 12'd40;
            5'd25 : En5_res = 12'd0;
            
            default: En5_res = 12'd0;
        endcase
    end
endmodule

src/Entropy_LUT_3x3.v
module Entropy_LUT_3x3(
    input wire [3:0] count,
    output reg [8:0] En3_res
);
    always @(*) begin
        case(count)
            4'd0:   En3_res = 9'd0;
            4'd1:   En3_res = 9'd250;
            4'd2:   En3_res = 9'd342;
            4'd3:   En3_res = 9'd375;
            4'd4:   En3_res = 9'd369;
            4'd5:   En3_res = 9'd334;
            4'd6:   En3_res = 9'd277;
            4'd7:   En3_res = 9'd200;
            4'd8:   En3_res = 9'd107;
            4'd9:   En3_res = 9'd0;
            
            default: En3_res = 9'd0;
            endcase 
        end
    endmodule

src/H1.v
module H1( //Tinh phan backgroumd
    input wire clk,
    input wire rst_n,
    input wire en,

    input wire [4:0] count,
    input wire clear,
    input wire mode,
    output reg [15:0] H1_res
);
    wire [3:0] bg_count_3x3;
    wire [4:0] bg_count_5x5;

    wire [8:0] En3_res;
    wire [11:0] En5_res;

    assign bg_count_3x3 = 4'd9 - count[3:0];
    assign bg_count_5x5 = 5'd25 - count;

    Entropy_LUT_3x3 inst1(
        .count(count[3:0]),
        .En3_res(En3_res)
    );

    Entropy_LUT_5x5 inst2(
        .count(count),
        .En5_res(En5_res)
    );

    always @(posedge clk or negedge rst_n) begin
        if(~rst_n) begin
            H1_res <= 16'd0;
        end
        else if(clear) begin
            H1_res <= 16'd0;
        end
        else begin
            if(en) begin
                H1_res <= H1_res + ((mode) ? En5_res : En3_res);
            end
        end
    end
endmodule

testbench/tb_H1.v
`timescale 1ns/1ps

module tb_H1;
    reg clk, rst_n, en, clear, mode;
    reg [4:0] count;
    wire [15:0] H1_res;
    reg [15:0] expected;
    integer errors;

    H1 uut (
        .clk(clk), .rst_n(rst_n), .en(en),
        .count(count), .clear(clear), .mode(mode),
        .H1_res(H1_res)
    );

    always #5 clk = ~clk;

    task apply_and_check;
        input [4:0] i_count;
        input i_mode;
        begin
            mode  = i_mode;
            count = i_count;
            clear = 1'b0;

            @(posedge clk);
            #1;

            if (mode == 1'b0)
                expected = expected + lut3(count[3:0]);
            else
                expected = expected + lut5(count);

            if (H1_res !== expected) begin
                errors = errors + 1;
                $display("[FAIL] t=%0t mode=%0d count=%0d H1_res=%0d expected=%0d",
                         $time, mode, count, H1_res, expected);
            end
            else begin
                $display("[PASS] t=%0t mode=%0d count=%0d H1_res=%0d",
                         $time, mode, count, H1_res);
            end
        end
    endtask

    function [15:0] lut3;
        input [3:0] c;
        begin
            case (c)
                4'd0: lut3 = 16'd0;
                4'd1: lut3 = 16'd250;
                4'd2: lut3 = 16'd342;
                4'd3: lut3 = 16'd375;
                4'd4: lut3 = 16'd369;
                4'd5: lut3 = 16'd334;
                4'd6: lut3 = 16'd277;
                4'd7: lut3 = 16'd200;
                4'd8: lut3 = 16'd107;
                default: lut3 = 16'd0;
            endcase
        end
    endfunction

    function [15:0] lut5;
        input [4:0] c;
        begin
            case (c)
                5'd0 : lut5 = 16'd0;
                5'd1 : lut5 = 16'd132;
                5'd2 : lut5 = 16'd207;
                5'd3 : lut5 = 16'd261;
                5'd4 : lut5 = 16'd300;
                5'd5 : lut5 = 16'd330;
                5'd6 : lut5 = 16'd351;
                5'd7 : lut5 = 16'd365;
                5'd8 : lut5 = 16'd373;
                5'd9 : lut5 = 16'd377;
                5'd10: lut5 = 16'd375;
                5'd11: lut5 = 16'd370;
                5'd12: lut5 = 16'd361;
                5'd13: lut5 = 16'd348;
                5'd14: lut5 = 16'd333;
                5'd15: lut5 = 16'd314;
                5'd16: lut5 = 16'd292;
                5'd17: lut5 = 16'd269;
                5'd18: lut5 = 16'd242;
                5'd19: lut5 = 16'd214;
                5'd20: lut5 = 16'd183;
                5'd21: lut5 = 16'd150;
                5'd22: lut5 = 16'd115;
                5'd23: lut5 = 16'd79;
                5'd24: lut5 = 16'd40;
                5'd25: lut5 = 16'd0;
                default: lut5 = 16'd0;
            endcase
        end
    endfunction

    initial begin
        $dumpfile("vcd/tb_H1.vcd");
        $dumpvars(0, tb_H1);

        clk = 1'b0;
        rst_n = 1'b0;
        en = 1'b0;
        clear = 1'b0;
        mode = 1'b0;
        count = 5'd0;
        expected = 16'd0;
        errors = 0;

        $display("\n==================== TB_H1 START ====================");

        repeat (2) @(posedge clk);
        rst_n = 1'b1;
        en   = 1'b1;

        // 3x3 mode checks
        apply_and_check(5'd3, 1'b0); // +375
        apply_and_check(5'd1, 1'b0); // +250 => 625
        apply_and_check(5'd0, 1'b0); // +0   => 625

        // clear behavior check
        clear = 1'b1;
        @(posedge clk);
        #1;
        expected = 16'd0;
        if (H1_res !== expected) begin
            errors = errors + 1;
            $display("[FAIL] t=%0t clear asserted H1_res=%0d expected=%0d", $time, H1_res, expected);
        end else begin
            $display("[PASS] t=%0t clear asserted H1_res=%0d", $time, H1_res);
        end
        clear = 1'b0;

        // 5x5 mode checks
        apply_and_check(5'd10, 1'b1); // +375
        apply_and_check(5'd2,  1'b1); // +207 => 582
        apply_and_check(5'd25, 1'b1); // +0   => 582

        if (errors == 0)
            $display("[RESULT] TB_H1 PASSED (no mismatches)");
        else
            $display("[RESULT] TB_H1 FAILED with %0d mismatch(es)", errors);

        $display("===================== TB_H1 END =====================\n");
        #10 $finish;
    end
endmodule

vcd/tb_H1.vcd
$date
	Mon Apr  6 14:54:16 2026
$end
$version
	Icarus Verilog
$end
$timescale
	1ps
$end
$scope module tb_H1 $end
$var wire 16 ! H1_res [15:0] $end
$var reg 1 " clear $end
$var reg 1 # clk $end
$var reg 5 $ count [4:0] $end
$var reg 1 % en $end
$var reg 16 & expected [15:0] $end
$var reg 1 ' mode $end
$var reg 1 ( rst_n $end
$var integer 32 ) errors [31:0] $end
$scope function lut3 $end
$var reg 4 * c [3:0] $end
$upscope $end
$scope function lut5 $end
$var reg 5 + c [4:0] $end
$upscope $end
$scope module uut $end
$var wire 1 " clear $end
$var wire 1 # clk $end
$var wire 5 , count [4:0] $end
$var wire 1 % en $end
$var wire 1 ' mode $end
$var wire 1 ( rst_n $end
$var wire 5 - bg_count_5x5 [4:0] $end
$var wire 4 . bg_count_3x3 [3:0] $end
$var wire 12 / En5_res [11:0] $end
$var wire 9 0 En3_res [8:0] $end
$var reg 16 1 H1_res [15:0] $end
$scope module inst1 $end
$var wire 4 2 count [3:0] $end
$var reg 9 3 En3_res [8:0] $end
$upscope $end
$scope module inst2 $end
$var wire 5 4 count [4:0] $end
$var reg 12 5 En5_res [11:0] $end
$upscope $end
$upscope $end
$scope task apply_and_check $end
$var reg 5 6 i_count [4:0] $end
$var reg 1 7 i_mode $end
$upscope $end
$upscope $end
$enddefinitions $end
$comment Show the parameter values. $end
$dumpall
$end
#0
$dumpvars
x7
bx 6
b0 5
b0 4
b0 3
b0 2
b0 1
b0 0
b0 /
b1001 .
b11001 -
b0 ,
bx +
bx *
b0 )
0(
0'
b0 &
0%
b0 $
0#
0"
b0 !
$end
#5000
1#
#10000
0#
#15000
b101110111 0
b101110111 3
b110 .
b11 2
b100000101 /
b100000101 5
b10110 -
b11 $
b11 ,
b11 4
07
b11 6
1%
1(
1#
#20000
0#
#25000
b101110111 !
b101110111 1
1#
#26000
b11111010 0
b11111010 3
b1000 .
b1 2
b10000100 /
b10000100 5
b11000 -
b1 $
b1 ,
b1 4
b1 6
b101110111 &
b11 *
#30000
0#
#35000
b1001110001 !
b1001110001 1
1#
#36000
b0 0
b0 3
b1001 .
b0 2
b0 /
b0 5
b11001 -
b0 $
b0 ,
b0 4
b0 6
b1001110001 &
b1 *
#40000
0#
#45000
1#
#46000
1"
b0 *
#50000
0#
#55000
b0 !
b0 1
1#
#56000
b1111 .
b1010 2
b101110111 /
b101110111 5
b1111 -
b1010 $
b1010 ,
b1010 4
1'
17
b1010 6
0"
b0 &
#60000
0#
#65000
b101110111 !
b101110111 1
1#
#66000
b101010110 0
b101010110 3
b111 .
b10 2
b11001111 /
b11001111 5
b10111 -
b10 $
b10 ,
b10 4
b10 6
b101110111 &
b1010 +
#70000
0#
#75000
b1001000110 !
b1001000110 1
1#
#76000
b0 0
b0 3
b0 .
b1001 2
b0 /
b0 5
b0 -
b11001 $
b11001 ,
b11001 4
b11001 6
b1001000110 &
b10 +
#80000
0#
#85000
1#
#86000
b11001 +
